yolov5_face/__init__.py
yolov5_face/_version.py
yolov5_face/detect_face.py
yolov5_face/detect_face_cli.py
yolov5_face/export.py
yolov5_face/hubconf.py
yolov5_face/optional.py
yolov5_face/test.py
yolov5_face/test_widerface.py
yolov5_face/train.py
yolov5_face/models/__init__.py
yolov5_face/models/blazeface.yaml
yolov5_face/models/blazeface_fpn.yaml
yolov5_face/models/common.py
yolov5_face/models/experimental.py
yolov5_face/models/yolo.py
yolov5_face/models/yolov5l.yaml
yolov5_face/models/yolov5l6.yaml
yolov5_face/models/yolov5m.yaml
yolov5_face/models/yolov5m6.yaml
yolov5_face/models/yolov5n-0.5.yaml
yolov5_face/models/yolov5n.yaml
yolov5_face/models/yolov5n6.yaml
yolov5_face/models/yolov5s.yaml
yolov5_face/models/yolov5s6.yaml
yolov5_face/utils/__init__.py
yolov5_face/utils/activations.py
yolov5_face/utils/autoanchor.py
yolov5_face/utils/datasets.py
yolov5_face/utils/face_datasets.py
yolov5_face/utils/general.py
yolov5_face/utils/google_utils.py
yolov5_face/utils/image.py
yolov5_face/utils/infer_utils.py
yolov5_face/utils/loss.py
yolov5_face/utils/metrics.py
yolov5_face/utils/plots.py
yolov5_face/utils/torch_utils.py
yolov5_face/utils/aws/__init__.py
yolov5_face/utils/aws/mime.sh
yolov5_face/utils/aws/resume.py
yolov5_face/utils/aws/userdata.sh
yolov5_face/utils/google_app_engine/Dockerfile
yolov5_face/utils/google_app_engine/additional_requirements.txt
yolov5_face/utils/google_app_engine/app.yaml
yolov5_face/utils/wandb_logging/__init__.py
yolov5_face/utils/wandb_logging/log_dataset.py
yolov5_face/utils/wandb_logging/wandb_utils.py
yolov5_face-0.0.2.dist-info/licenses/LICENSE
yolov5_face-0.0.2.dist-info/METADATA
yolov5_face-0.0.2.dist-info/WHEEL
yolov5_face-0.0.2.dist-info/entry_points.txt
yolov5_face-0.0.2.dist-info/top_level.txt
yolov5_face-0.0.2.dist-info/RECORD
