Metadata-Version: 2.4
Name: yolov5-face
Version: 0.0.2
Summary: Real-time face detection using YOLOv5 - Fork
License: GPL-3.0
Project-URL: website, https://github.com/deepcam-cn/yolov5-face/
Classifier: License :: OSI Approved :: GNU General Public License v3 (GPLv3)
Classifier: Programming Language :: Python :: 3
Classifier: Programming Language :: Python :: 3.10
Classifier: Programming Language :: Python :: 3.11
Classifier: Programming Language :: Python :: 3.12
Requires-Python: <3.13,>=3.10
License-File: LICENSE
Requires-Dist: numpy
Requires-Dist: opencv-contrib-python
Requires-Dist: pyyaml
Requires-Dist: torch
Requires-Dist: torchvision
Provides-Extra: cli
Requires-Dist: pillow; extra == "cli"
Requires-Dist: requests; extra == "cli"
Requires-Dist: tqdm; extra == "cli"
Provides-Extra: train
Requires-Dist: matplotlib; extra == "train"
Requires-Dist: onnx; extra == "train"
Requires-Dist: onnxruntime; extra == "train"
Requires-Dist: pandas; extra == "train"
Requires-Dist: pillow; extra == "train"
Requires-Dist: requests; extra == "train"
Requires-Dist: scipy; extra == "train"
Requires-Dist: seaborn; extra == "train"
Requires-Dist: tensorboard; extra == "train"
Requires-Dist: tqdm; extra == "train"
Requires-Dist: wandb; extra == "train"
Dynamic: license-file
